instastorysaver/__init__.py
instastorysaver/auth.py
instastorysaver/main.py
instastorysaver-0.1.2.dist-info/METADATA
instastorysaver-0.1.2.dist-info/WHEEL
instastorysaver-0.1.2.dist-info/entry_points.txt
instastorysaver-0.1.2.dist-info/top_level.txt
instastorysaver-0.1.2.dist-info/RECORD
