Metadata-Version: 2.2
Name: instastorysaver
Version: 0.1.2
Summary: Instagram Story Saver
Home-page: https://github.com/Hansel11/instagram-story-saver
Author: Hansel11
Requires-Dist: annotated-types==0.7.0
Requires-Dist: certifi==2024.12.14
Requires-Dist: charset-normalizer==3.4.1
Requires-Dist: idna==3.10
Requires-Dist: instagrapi==2.1.3
Requires-Dist: pillow==11.1.0
Requires-Dist: pycryptodomex==3.21.0
Requires-Dist: pydantic==2.10.1
Requires-Dist: pydantic_core==2.27.1
Requires-Dist: PySocks==1.7.1
Requires-Dist: requests==2.32.3
Requires-Dist: setuptools==75.8.0
Requires-Dist: typing_extensions==4.12.2
Requires-Dist: urllib3==2.3.0
Dynamic: author
Dynamic: description
Dynamic: description-content-type
Dynamic: home-page
Dynamic: requires-dist
Dynamic: summary
